alfred3_reaction_times/__init__.py
alfred3_reaction_times/_env.py
alfred3_reaction_times/_version.py
alfred3_reaction_times/hidden_input.py
alfred3_reaction_times/keycodes.py
alfred3_reaction_times/reaction_times.py
alfred3_reaction_times/sequence_part.py
alfred3_reaction_times/trial.py
alfred3_reaction_times/css/__init__.py
alfred3_reaction_times/css/layout.css
alfred3_reaction_times/js/__init__.py
alfred3_reaction_times/js/main.js
alfred3_reaction_times/templates/EmptyBaseElement.html.j2
alfred3_reaction_times/templates/HiddenInput.html.j2
alfred3_reaction_times/templates/Reaction.html.j2
alfred3_reaction_times/templates/ReactionTimes.html.j2
alfred3_reaction_times/templates/SequencePart.html.j2
alfred3_reaction_times/templates/Stimulus.html.j2
alfred3_reaction_times/templates/Trial.html.j2
alfred3_reaction_times-0.1.6.dist-info/LICENSE
alfred3_reaction_times-0.1.6.dist-info/METADATA
alfred3_reaction_times-0.1.6.dist-info/WHEEL
alfred3_reaction_times-0.1.6.dist-info/top_level.txt
alfred3_reaction_times-0.1.6.dist-info/RECORD
