Metadata-Version: 2.1
Name: alfred3-reaction-times
Version: 0.1.6
Summary: Alfred3 library for measurement of reaction times.
Home-page: https://github.com/mate-code/alfred3-reaction-times
Author: Marius Teller
Author-email: marius.teller@psych.uni-goettingen.de
Project-URL: Bug Tracker, https://github.com/mate-code/alfred3-reaction-times/issues
Classifier: Programming Language :: Python :: 3
Classifier: License :: OSI Approved :: MIT License
Classifier: Operating System :: OS Independent
Requires-Python: >=3.7
License-File: LICENSE
Requires-Dist: alfred3 (>="2.3.1")
Requires-Dist: jinja2 (>="2.11")
